robot_brains/C_gen.py
robot_brains/C_preamble
robot_brains/__init__.py
robot_brains/code_generator.py
robot_brains/parser.py
robot_brains/parsetab.py
robot_brains/scanner.py
robot_brains/symtable.py
robot_brains-0.1.0.dist-info/LICENSE
robot_brains-0.1.0.dist-info/METADATA
robot_brains-0.1.0.dist-info/WHEEL
robot_brains-0.1.0.dist-info/entry_points.txt
robot_brains-0.1.0.dist-info/top_level.txt
robot_brains-0.1.0.dist-info/RECORD
