Metadata-Version: 2.1
Name: robot-brains
Version: 0.1.0
Summary: FTC alternative robot programming language
Home-page: https://github.com/dangyogi/robot-brains.git
Author: Bruce Frederiksen
Author-email: dangyogi@gmail.com
License: MIT License
Keywords: FTC robot programming blockly
Platform: UNKNOWN
Classifier: Development Status :: 2 - Pre-Alpha
Classifier: Environment :: Console
Classifier: Intended Audience :: Developers
Classifier: Intended Audience :: Education
Classifier: License :: OSI Approved :: MIT License
Classifier: Natural Language :: English
Classifier: Operating System :: OS Independent
Classifier: Programming Language :: Python :: 3
Classifier: Topic :: Education
Classifier: Topic :: Scientific/Engineering
Classifier: Topic :: Software Development :: Code Generators
Classifier: Topic :: Software Development :: Compilers
Classifier: Topic :: Software Development :: Embedded Systems
Requires-Dist: ply (>=3.11)
